ai_yardstick/__init__.py
ai_yardstick/__main__.py
ai_yardstick/cli.py
ai_yardstick-0.0.1.dist-info/licenses/LICENSE
ai_yardstick-0.0.1.dist-info/METADATA
ai_yardstick-0.0.1.dist-info/WHEEL
ai_yardstick-0.0.1.dist-info/entry_points.txt
ai_yardstick-0.0.1.dist-info/top_level.txt
ai_yardstick-0.0.1.dist-info/RECORD
