Metadata-Version: 2.4
Name: ai-yardstick
Version: 0.0.1
Summary: A CLI tool for running and managing LLM evaluations
Author: Kevin Schaul
License: MIT
Project-URL: Homepage, https://github.com/kevinschaul/ai-yardstick
Project-URL: Changelog, https://github.com/kevinschaul/ai-yardstick/releases
Project-URL: Issues, https://github.com/kevinschaul/ai-yardstick/issues
Project-URL: CI, https://github.com/kevinschaul/ai-yardstick/actions
Requires-Python: >=3.9
License-File: LICENSE
Requires-Dist: click
Requires-Dist: llm>=0.24
Requires-Dist: pandas>=2.2
Requires-Dist: pydantic_evals>=0.1.3
Provides-Extra: test
Requires-Dist: pytest; extra == "test"
Dynamic: license-file
